pysnarf/__init__.py
pysnarf-0.1.1.dist-info/entry_points.txt
pysnarf-0.1.1.dist-info/LICENSE
pysnarf-0.1.1.dist-info/METADATA
pysnarf-0.1.1.dist-info/WHEEL
pysnarf-0.1.1.dist-info/RECORD
